[{"filename": "DJI_0085.JPG", "mask": null, "width": 4000, "height": 3000, "camera_make": "DJI", "camera_model": "FC7203", "orientation": 1, "latitude": -37.784042166666666, "longitude": -58.338330722222224, "altitude": 78.47, "band_name": "RGB", "band_index": 0, "capture_uuid": null, "fnumber": 2.8, "radiometric_calibration": null, "black_level": null, "gain": null, "gain_adjustment": null, "exposure_time": 0.0015625, "iso_speed": 100, "bits_per_sample": null, "vignetting_center": null, "vignetting_polynomial": null, "spectral_irradiance": null, "horizontal_irradiance": null, "irradiance_scale_to_si": null, "utc_time": 1729245103000.0, "yaw": 41.8, "pitch": 9.099999999999994, "roll": 0.0, "omega": -6.0887552248169765, "phi": 0.9773471352894121, "kappa": 169.98667314562422, "sun_sensor": null, "dls_yaw": null, "dls_pitch": null, "dls_roll": null, "speed_x": -0.6000000238418579, "speed_y": 0.699999988079071, "speed_z": 0.0, "exif_width": 4000, "exif_height": 3000, "gps_xy_stddev": null, "gps_z_stddev": null, "camera_projection": "brown", "focal_ratio": 0.6666666666666666}, {"filename": "DJI_0069.JPG", "mask": null, "width": 4000, "height": 3000, "camera_make": "DJI", "camera_model": "FC7203", "orientation": 1, "latitude": -37.78435552777778, "longitude": -58.338699777777784, "altitude": 78.07, "band_name": "RGB", "band_index": 0, "capture_uuid": null, "fnumber": 2.8, "radiometric_calibration": null, "black_level": null, "gain": null, "gain_adjustment": null, "exposure_time": 0.0015625, "iso_speed": 100, "bits_per_sample": null, "vignetting_center": null, "vignetting_polynomial": null, "spectral_irradiance": null, "horizontal_irradiance": null, "irradiance_scale_to_si": null, "utc_time": 1729245071000.0, "yaw": 42.1, "pitch": 0.0, "roll": 0.0, "omega": -0.0, "phi": 0.0, "kappa": 169.56129953843333, "sun_sensor": null, "dls_yaw": null, "dls_pitch": null, "dls_roll": null, "speed_x": 2.200000047683716, "speed_y": 2.0, "speed_z": 0.0, "exif_width": 4000, "exif_height": 3000, "gps_xy_stddev": null, "gps_z_stddev": null, "camera_projection": "brown", "focal_ratio": 0.6666666666666666}, {"filename": "DJI_0086.JPG", "mask": null, "width": 4000, "height": 3000, "camera_make": "DJI", "camera_model": "FC7203", "orientation": 1, "latitude": -37.78405844444444, "longitude": -58.33830691666667, "altitude": 78.57, "band_name": "RGB", "band_index": 0, "capture_uuid": null, "fnumber": 2.8, "radiometric_calibration": null, "black_level": null, "gain": null, "gain_adjustment": null, "exposure_time": 0.0015625, "iso_speed": 100, "bits_per_sample": null, "vignetting_center": null, "vignetting_polynomial": null, "spectral_irradiance": null, "horizontal_irradiance": null, "irradiance_scale_to_si": null, "utc_time": 1729245105000.0, "yaw": 42.0, "pitch": 9.099999999999994, "roll": 0.0, "omega": -6.082981553417779, "phi": 0.9964194704210577, "kappa": 169.78906020909227, "sun_sensor": null, "dls_yaw": null, "dls_pitch": null, "dls_roll": null, "speed_x": -1.0, "speed_y": 1.2000000476837158, "speed_z": 0.0, "exif_width": 4000, "exif_height": 3000, "gps_xy_stddev": null, "gps_z_stddev": null, "camera_projection": "brown", "focal_ratio": 0.6666666666666666}, {"filename": "DJI_0074.JPG", "mask": null, "width": 4000, "height": 3000, "camera_make": "DJI", "camera_model": "FC7203", "orientation": 1, "latitude": -37.78411783333333, "longitude": -58.33843080555556, "altitude": 78.27, "band_name": "RGB", "band_index": 0, "capture_uuid": null, "fnumber": 2.8, "radiometric_calibration": null, "black_level": null, "gain": null, "gain_adjustment": null, "exposure_time": 0.00125, "iso_speed": 100, "bits_per_sample": null, "vignetting_center": null, "vignetting_polynomial": null, "spectral_irradiance": null, "horizontal_irradiance": null, "irradiance_scale_to_si": null, "utc_time": 1729245081000.0, "yaw": 42.1, "pitch": 0.09999999999999432, "roll": 0.0, "omega": -0.06031657990745395, "phi": 0.011100604259788394, "kappa": 169.56158396985586, "sun_sensor": null, "dls_yaw": null, "dls_pitch": null, "dls_roll": null, "speed_x": 2.5, "speed_y": 2.200000047683716, "speed_z": 0.0, "exif_width": 4000, "exif_height": 3000, "gps_xy_stddev": null, "gps_z_stddev": null, "camera_projection": "brown", "focal_ratio": 0.6666666666666666}, {"filename": "DJI_0082.JPG", "mask": null, "width": 4000, "height": 3000, "camera_make": "DJI", "camera_model": "FC7203", "orientation": 1, "latitude": -37.78401980555555, "longitude": -58.33832338888889, "altitude": 79.07, "band_name": "RGB", "band_index": 0, "capture_uuid": null, "fnumber": 2.8, "radiometric_calibration": null, "black_level": null, "gain": null, "gain_adjustment": null, "exposure_time": 0.0015625, "iso_speed": 100, "bits_per_sample": null, "vignetting_center": null, "vignetting_polynomial": null, "spectral_irradiance": null, "horizontal_irradiance": null, "irradiance_scale_to_si": null, "utc_time": 1729245097000.0, "yaw": 42.1, "pitch": 9.099999999999994, "roll": 0.0, "omega": -6.0800590058168416, "phi": 1.0059531030477369, "kappa": 169.6902200840609, "sun_sensor": null, "dls_yaw": null, "dls_pitch": null, "dls_roll": null, "speed_x": -1.7000000476837158, "speed_y": -1.5, "speed_z": 0.0, "exif_width": 4000, "exif_height": 3000, "gps_xy_stddev": null, "gps_z_stddev": null, "camera_projection": "brown", "focal_ratio": 0.6666666666666666}, {"filename": "DJI_0079.JPG", "mask": null, "width": 4000, "height": 3000, "camera_make": "DJI", "camera_model": "FC7203", "orientation": 1, "latitude": -37.78398241666667, "longitude": -58.338281055555555, "altitude": 78.87, "band_name": "RGB", "band_index": 0, "capture_uuid": null, "fnumber": 2.8, "radiometric_calibration": null, "black_level": null, "gain": null, "gain_adjustment": null, "exposure_time": 0.0015625, "iso_speed": 100, "bits_per_sample": null, "vignetting_center": null, "vignetting_polynomial": null, "spectral_irradiance": null, "horizontal_irradiance": null, "irradiance_scale_to_si": null, "utc_time": 1729245091000.0, "yaw": 42.1, "pitch": 9.099999999999994, "roll": 0.0, "omega": -6.080054974104099, "phi": 1.0059481041298073, "kappa": 169.69026293135389, "sun_sensor": null, "dls_yaw": null, "dls_pitch": null, "dls_roll": null, "speed_x": -0.10000000149011612, "speed_y": -0.10000000149011612, "speed_z": 0.0, "exif_width": 4000, "exif_height": 3000, "gps_xy_stddev": null, "gps_z_stddev": null, "camera_projection": "brown", "focal_ratio": 0.6666666666666666}, {"filename": "DJI_0072.JPG", "mask": null, "width": 4000, "height": 3000, "camera_make": "DJI", "camera_model": "FC7203", "orientation": 1, "latitude": -37.78421158333333, "longitude": -58.338538222222226, "altitude": 78.07, "band_name": "RGB", "band_index": 0, "capture_uuid": null, "fnumber": 2.8, "radiometric_calibration": null, "black_level": null, "gain": null, "gain_adjustment": null, "exposure_time": 0.00125, "iso_speed": 100, "bits_per_sample": null, "vignetting_center": null, "vignetting_polynomial": null, "spectral_irradiance": null, "horizontal_irradiance": null, "irradiance_scale_to_si": null, "utc_time": 1729245077000.0, "yaw": 42.0, "pitch": 0.09999999999999432, "roll": 0.0, "omega": -0.060336088284569635, "phi": 0.010995560005972507, "kappa": 169.6614760183468, "sun_sensor": null, "dls_yaw": null, "dls_pitch": null, "dls_roll": null, "speed_x": 2.5999999046325684, "speed_y": 2.299999952316284, "speed_z": 0.0, "exif_width": 4000, "exif_height": 3000, "gps_xy_stddev": null, "gps_z_stddev": null, "camera_projection": "brown", "focal_ratio": 0.6666666666666666}, {"filename": "DJI_0083.JPG", "mask": null, "width": 4000, "height": 3000, "camera_make": "DJI", "camera_model": "FC7203", "orientation": 1, "latitude": -37.784035277777775, "longitude": -58.338341722222225, "altitude": 78.87, "band_name": "RGB", "band_index": 0, "capture_uuid": null, "fnumber": 2.8, "radiometric_calibration": null, "black_level": null, "gain": null, "gain_adjustment": null, "exposure_time": 0.0015625, "iso_speed": 100, "bits_per_sample": null, "vignetting_center": null, "vignetting_polynomial": null, "spectral_irradiance": null, "horizontal_irradiance": null, "irradiance_scale_to_si": null, "utc_time": 1729245099000.0, "yaw": 42.2, "pitch": 9.099999999999994, "roll": 0.0, "omega": -6.0771245729664845, "phi": 1.0154849799570942, "kappa": 169.5913788585765, "sun_sensor": null, "dls_yaw": null, "dls_pitch": null, "dls_roll": null, "speed_x": 0.0, "speed_y": -0.10000000149011612, "speed_z": 0.0, "exif_width": 4000, "exif_height": 3000, "gps_xy_stddev": null, "gps_z_stddev": null, "camera_projection": "brown", "focal_ratio": 0.6666666666666666}, {"filename": "DJI_0073.JPG", "mask": null, "width": 4000, "height": 3000, "camera_make": "DJI", "camera_model": "FC7203", "orientation": 1, "latitude": -37.78416466666666, "longitude": -58.33848402777778, "altitude": 78.27, "band_name": "RGB", "band_index": 0, "capture_uuid": null, "fnumber": 2.8, "radiometric_calibration": null, "black_level": null, "gain": null, "gain_adjustment": null, "exposure_time": 0.00125, "iso_speed": 100, "bits_per_sample": null, "vignetting_center": null, "vignetting_polynomial": null, "spectral_irradiance": null, "horizontal_irradiance": null, "irradiance_scale_to_si": null, "utc_time": 1729245079000.0, "yaw": 42.1, "pitch": 0.09999999999999432, "roll": 0.0, "omega": -0.06031663558509739, "phi": 0.011100672430845024, "kappa": 169.5615307052642, "sun_sensor": null, "dls_yaw": null, "dls_pitch": null, "dls_roll": null, "speed_x": 2.5, "speed_y": 2.299999952316284, "speed_z": 0.0, "exif_width": 4000, "exif_height": 3000, "gps_xy_stddev": null, "gps_z_stddev": null, "camera_projection": "brown", "focal_ratio": 0.6666666666666666}, {"filename": "DJI_0071.JPG", "mask": null, "width": 4000, "height": 3000, "camera_make": "DJI", "camera_model": "FC7203", "orientation": 1, "latitude": -37.784260777777774, "longitude": -58.338593555555555, "altitude": 77.97, "band_name": "RGB", "band_index": 0, "capture_uuid": null, "fnumber": 2.8, "radiometric_calibration": null, "black_level": null, "gain": null, "gain_adjustment": null, "exposure_time": 0.00125, "iso_speed": 100, "bits_per_sample": null, "vignetting_center": null, "vignetting_polynomial": null, "spectral_irradiance": null, "horizontal_irradiance": null, "irradiance_scale_to_si": null, "utc_time": 1729245075000.0, "yaw": 42.0, "pitch": 0.09999999999999432, "roll": 0.0, "omega": -0.06033614428092048, "phi": 0.010995625877651157, "kappa": 169.66142481332972, "sun_sensor": null, "dls_yaw": null, "dls_pitch": null, "dls_roll": null, "speed_x": 2.700000047683716, "speed_y": 2.4000000953674316, "speed_z": 0.0, "exif_width": 4000, "exif_height": 3000, "gps_xy_stddev": null, "gps_z_stddev": null, "camera_projection": "brown", "focal_ratio": 0.6666666666666666}, {"filename": "DJI_0078.JPG", "mask": null, "width": 4000, "height": 3000, "camera_make": "DJI", "camera_model": "FC7203", "orientation": 1, "latitude": -37.78397861111111, "longitude": -58.33827388888889, "altitude": 78.77, "band_name": "RGB", "band_index": 0, "capture_uuid": null, "fnumber": 2.8, "radiometric_calibration": null, "black_level": null, "gain": null, "gain_adjustment": null, "exposure_time": 0.0015625, "iso_speed": 100, "bits_per_sample": null, "vignetting_center": null, "vignetting_polynomial": null, "spectral_irradiance": null, "horizontal_irradiance": null, "irradiance_scale_to_si": null, "utc_time": 1729245089000.0, "yaw": 42.0, "pitch": 9.099999999999994, "roll": 0.0, "omega": -6.082972227706289, "phi": 0.9964146854617258, "kappa": 169.78909167131468, "sun_sensor": null, "dls_yaw": null, "dls_pitch": null, "dls_roll": null, "speed_x": -0.10000000149011612, "speed_y": -0.20000000298023224, "speed_z": 0.0, "exif_width": 4000, "exif_height": 3000, "gps_xy_stddev": null, "gps_z_stddev": null, "camera_projection": "brown", "focal_ratio": 0.6666666666666666}, {"filename": "DJI_0081.JPG", "mask": null, "width": 4000, "height": 3000, "camera_make": "DJI", "camera_model": "FC7203", "orientation": 1, "latitude": -37.783992749999996, "longitude": -58.33829436111111, "altitude": 78.87, "band_name": "RGB", "band_index": 0, "capture_uuid": null, "fnumber": 2.8, "radiometric_calibration": null, "black_level": null, "gain": null, "gain_adjustment": null, "exposure_time": 0.0015625, "iso_speed": 100, "bits_per_sample": null, "vignetting_center": null, "vignetting_polynomial": null, "spectral_irradiance": null, "horizontal_irradiance": null, "irradiance_scale_to_si": null, "utc_time": 1729245095000.0, "yaw": 41.9, "pitch": 9.099999999999994, "roll": 0.0, "omega": -6.085871064536293, "phi": 0.9868811683146305, "kappa": 169.88789144114884, "sun_sensor": null, "dls_yaw": null, "dls_pitch": null, "dls_roll": null, "speed_x": -0.8999999761581421, "speed_y": -0.8999999761581421, "speed_z": 0.0, "exif_width": 4000, "exif_height": 3000, "gps_xy_stddev": null, "gps_z_stddev": null, "camera_projection": "brown", "focal_ratio": 0.6666666666666666}, {"filename": "DJI_0084.JPG", "mask": null, "width": 4000, "height": 3000, "camera_make": "DJI", "camera_model": "FC7203", "orientation": 1, "latitude": -37.78403561111111, "longitude": -58.33834127777778, "altitude": 78.57, "band_name": "RGB", "band_index": 0, "capture_uuid": null, "fnumber": 2.8, "radiometric_calibration": null, "black_level": null, "gain": null, "gain_adjustment": null, "exposure_time": 0.0015625, "iso_speed": 100, "bits_per_sample": null, "vignetting_center": null, "vignetting_polynomial": null, "spectral_irradiance": null, "horizontal_irradiance": null, "irradiance_scale_to_si": null, "utc_time": 1729245101000.0, "yaw": 41.8, "pitch": 9.099999999999994, "roll": 0.0, "omega": -6.088753752641867, "phi": 0.9773479574605108, "kappa": 169.9866623660153, "sun_sensor": null, "dls_yaw": null, "dls_pitch": null, "dls_roll": null, "speed_x": 0.0, "speed_y": 0.0, "speed_z": 0.0, "exif_width": 4000, "exif_height": 3000, "gps_xy_stddev": null, "gps_z_stddev": null, "camera_projection": "brown", "focal_ratio": 0.6666666666666666}, {"filename": "DJI_0077.JPG", "mask": null, "width": 4000, "height": 3000, "camera_make": "DJI", "camera_model": "FC7203", "orientation": 1, "latitude": -37.78398102777778, "longitude": -58.33827638888889, "altitude": 78.57, "band_name": "RGB", "band_index": 0, "capture_uuid": null, "fnumber": 2.8, "radiometric_calibration": null, "black_level": null, "gain": null, "gain_adjustment": null, "exposure_time": 0.0015625, "iso_speed": 100, "bits_per_sample": null, "vignetting_center": null, "vignetting_polynomial": null, "spectral_irradiance": null, "horizontal_irradiance": null, "irradiance_scale_to_si": null, "utc_time": 1729245087000.0, "yaw": 42.0, "pitch": 0.0, "roll": 0.0, "omega": -0.0, "phi": 0.0, "kappa": 169.66172292763, "sun_sensor": null, "dls_yaw": null, "dls_pitch": null, "dls_roll": null, "speed_x": 1.399999976158142, "speed_y": 1.2000000476837158, "speed_z": -0.10000000149011612, "exif_width": 4000, "exif_height": 3000, "gps_xy_stddev": null, "gps_z_stddev": null, "camera_projection": "brown", "focal_ratio": 0.6666666666666666}, {"filename": "DJI_0068.JPG", "mask": null, "width": 4000, "height": 3000, "camera_make": "DJI", "camera_model": "FC7203", "orientation": 1, "latitude": -37.78439175, "longitude": -58.338738194444446, "altitude": 78.27, "band_name": "RGB", "band_index": 0, "capture_uuid": null, "fnumber": 2.8, "radiometric_calibration": null, "black_level": null, "gain": null, "gain_adjustment": null, "exposure_time": 0.00125, "iso_speed": 100, "bits_per_sample": null, "vignetting_center": null, "vignetting_polynomial": null, "spectral_irradiance": null, "horizontal_irradiance": null, "irradiance_scale_to_si": null, "utc_time": 1729245069000.0, "yaw": 48.0, "pitch": 0.0, "roll": 0.0, "omega": -0.0, "phi": 0.0, "kappa": 163.66126235934075, "sun_sensor": null, "dls_yaw": null, "dls_pitch": null, "dls_roll": null, "speed_x": 1.2000000476837158, "speed_y": 1.2999999523162842, "speed_z": 0.0, "exif_width": 4000, "exif_height": 3000, "gps_xy_stddev": null, "gps_z_stddev": null, "camera_projection": "brown", "focal_ratio": 0.6666666666666666}, {"filename": "DJI_0087.JPG", "mask": null, "width": 4000, "height": 3000, "camera_make": "DJI", "camera_model": "FC7203", "orientation": 1, "latitude": -37.78407977777778, "longitude": -58.33827538888889, "altitude": 78.67, "band_name": "RGB", "band_index": 0, "capture_uuid": null, "fnumber": 2.8, "radiometric_calibration": null, "black_level": null, "gain": null, "gain_adjustment": null, "exposure_time": 0.0015625, "iso_speed": 100, "bits_per_sample": null, "vignetting_center": null, "vignetting_polynomial": null, "spectral_irradiance": null, "horizontal_irradiance": null, "irradiance_scale_to_si": null, "utc_time": 1729245107000.0, "yaw": 42.8, "pitch": 9.099999999999994, "roll": 0.0, "omega": -6.059107192236409, "phi": 1.0725925826305147, "kappa": 168.9984724927784, "sun_sensor": null, "dls_yaw": null, "dls_pitch": null, "dls_roll": null, "speed_x": -0.699999988079071, "speed_y": 0.8999999761581421, "speed_z": 0.0, "exif_width": 4000, "exif_height": 3000, "gps_xy_stddev": null, "gps_z_stddev": null, "camera_projection": "brown", "focal_ratio": 0.6666666666666666}, {"filename": "DJI_0075.JPG", "mask": null, "width": 4000, "height": 3000, "camera_make": "DJI", "camera_model": "FC7203", "orientation": 1, "latitude": -37.78407144444444, "longitude": -58.338378500000005, "altitude": 78.37, "band_name": "RGB", "band_index": 0, "capture_uuid": null, "fnumber": 2.8, "radiometric_calibration": null, "black_level": null, "gain": null, "gain_adjustment": null, "exposure_time": 0.00125, "iso_speed": 100, "bits_per_sample": null, "vignetting_center": null, "vignetting_polynomial": null, "spectral_irradiance": null, "horizontal_irradiance": null, "irradiance_scale_to_si": null, "utc_time": 1729245083000.0, "yaw": 42.2, "pitch": 0.09999999999999432, "roll": 0.0, "omega": -0.06029694190914388, "phi": 0.011205683646267112, "kappa": 169.46163737678089, "sun_sensor": null, "dls_yaw": null, "dls_pitch": null, "dls_roll": null, "speed_x": 2.5, "speed_y": 2.200000047683716, "speed_z": 0.0, "exif_width": 4000, "exif_height": 3000, "gps_xy_stddev": null, "gps_z_stddev": null, "camera_projection": "brown", "focal_ratio": 0.6666666666666666}, {"filename": "DJI_0076.JPG", "mask": null, "width": 4000, "height": 3000, "camera_make": "DJI", "camera_model": "FC7203", "orientation": 1, "latitude": -37.784025194444446, "longitude": -58.33832588888889, "altitude": 78.67, "band_name": "RGB", "band_index": 0, "capture_uuid": null, "fnumber": 2.8, "radiometric_calibration": null, "black_level": null, "gain": null, "gain_adjustment": null, "exposure_time": 0.0015625, "iso_speed": 100, "bits_per_sample": null, "vignetting_center": null, "vignetting_polynomial": null, "spectral_irradiance": null, "horizontal_irradiance": null, "irradiance_scale_to_si": null, "utc_time": 1729245085000.0, "yaw": 42.2, "pitch": 0.0, "roll": 0.0, "omega": -0.0, "phi": 0.0, "kappa": 169.46167378136855, "sun_sensor": null, "dls_yaw": null, "dls_pitch": null, "dls_roll": null, "speed_x": 2.5, "speed_y": 2.200000047683716, "speed_z": 0.0, "exif_width": 4000, "exif_height": 3000, "gps_xy_stddev": null, "gps_z_stddev": null, "camera_projection": "brown", "focal_ratio": 0.6666666666666666}, {"filename": "DJI_0080.JPG", "mask": null, "width": 4000, "height": 3000, "camera_make": "DJI", "camera_model": "FC7203", "orientation": 1, "latitude": -37.783984305555556, "longitude": -58.338283833333335, "altitude": 78.77, "band_name": "RGB", "band_index": 0, "capture_uuid": null, "fnumber": 2.8, "radiometric_calibration": null, "black_level": null, "gain": null, "gain_adjustment": null, "exposure_time": 0.0015625, "iso_speed": 100, "bits_per_sample": null, "vignetting_center": null, "vignetting_polynomial": null, "spectral_irradiance": null, "horizontal_irradiance": null, "irradiance_scale_to_si": null, "utc_time": 1729245093000.0, "yaw": 42.0, "pitch": 9.099999999999994, "roll": 0.0, "omega": -6.082972555304669, "phi": 0.9964156442936931, "kappa": 169.78908265108532, "sun_sensor": null, "dls_yaw": null, "dls_pitch": null, "dls_roll": null, "speed_x": 0.0, "speed_y": 0.0, "speed_z": 0.0, "exif_width": 4000, "exif_height": 3000, "gps_xy_stddev": null, "gps_z_stddev": null, "camera_projection": "brown", "focal_ratio": 0.6666666666666666}, {"filename": "DJI_0070.JPG", "mask": null, "width": 4000, "height": 3000, "camera_make": "DJI", "camera_model": "FC7203", "orientation": 1, "latitude": -37.78431027777778, "longitude": -58.33864925, "altitude": 77.97, "band_name": "RGB", "band_index": 0, "capture_uuid": null, "fnumber": 2.8, "radiometric_calibration": null, "black_level": null, "gain": null, "gain_adjustment": null, "exposure_time": 0.00125, "iso_speed": 100, "bits_per_sample": null, "vignetting_center": null, "vignetting_polynomial": null, "spectral_irradiance": null, "horizontal_irradiance": null, "irradiance_scale_to_si": null, "utc_time": 1729245073000.0, "yaw": 42.1, "pitch": 0.09999999999999432, "roll": 0.0, "omega": -0.060316803613631294, "phi": 0.011100882574044627, "kappa": 169.56136590312832, "sun_sensor": null, "dls_yaw": null, "dls_pitch": null, "dls_roll": null, "speed_x": 2.5, "speed_y": 2.200000047683716, "speed_z": 0.0, "exif_width": 4000, "exif_height": 3000, "gps_xy_stddev": null, "gps_z_stddev": null, "camera_projection": "brown", "focal_ratio": 0.6666666666666666}]